moralizer/__init__.py
moralizer/auxilliary_functions.py
moralizer/moral_foundations.json
moralizer/moralizer.py
moralizer/practice_text.txt
moralizer-0.1.4.dist-info/LICENSE
moralizer-0.1.4.dist-info/WHEEL
moralizer-0.1.4.dist-info/METADATA
moralizer-0.1.4.dist-info/RECORD
