Metadata-Version: 2.1
Name: moralizer
Version: 0.1.4
Summary: > Simple tool to get the Moral Foundations counts of a given text.
Home-page: https://github.com/npmontgomery/moralizer
License: MIT
Keywords: nlp,sentiment,spacy,moral foundations
Author: npm
Requires-Python: >=3.6,<4.0
Classifier: License :: OSI Approved :: MIT License
Classifier: Natural Language :: English
Classifier: Programming Language :: Python :: 3
Classifier: Programming Language :: Python :: 3.6
Classifier: Programming Language :: Python :: 3.7
Requires-Dist: spacy (>=2.1,<3.0)
Project-URL: Documentation, https://github.com/npmontgomery/moralizer
Project-URL: Repository, https://github.com/npmontgomery/moralizer
